chronik/__init__.py
chronik/alp.py
chronik/chronik_pb2.py
chronik/client.py
chronik/slp.py
chronik/test_data.py
chronik/token_tx.py
chronik_client-0.0.1.dist-info/METADATA
chronik_client-0.0.1.dist-info/WHEEL
chronik_client-0.0.1.dist-info/top_level.txt
chronik_client-0.0.1.dist-info/RECORD
